Workbook

Sheet 封面说明
B2: Quick Audience 商家分层练习 · 模拟数据（Mock Data）
B3: 瓴羊 Quick Audience：数据×AI 智能营销平台｜收入 = 系统订阅 + 通道按消耗计费（短信 / AI外呼 / Push / 企微）
B5: 关键数据概览
B6: 商家总数（家） | E6: =COUNTA(商家明细!A2:A2001) -> 2000
B7: 有消耗商家（家） | E7: =COUNTIF(商家明细!M2:M2001,">0") -> 1370
B8: 未激活商家（近12月消耗为0） | E8: =COUNTIF(商家明细!M2:M2001,0) -> 630
B9: 近12月通道总消耗（元） | E9: =SUM(商家明细!M2:M2001) -> 190743600
B10: 年消耗>500万的商家（SKA候选） | E10: =COUNTIF(商家明细!M2:M2001,">5000000") -> 4
B11: 年消耗>100万商家的消耗占比 | E11: =SUMIF(商家明细!M2:M2001,">1000000")/SUM(商家明细!M2:M2001) -> 0.46834389
B13: Sheet 导航
B14: 字段字典与作业指引 | C14: 24个字段口径说明 + 四种分层方法的练习取数建议
B15: 打分卡 | C15: 指标体系 · 权重 · 分档口径 · 分层映射规则（公式的配置源）
B16: 商家明细 | C16: 2000家商家明细 + 18列内嵌公式（档位分→综合分→层级→通道策略）
B17: 分层结果与业务动作 | C17: 分层汇总统计（活公式）+ 结构验证 + 分层×通道动作表
B20: 说明：本数据为模拟生成，仅用于课堂分层练习，与瓴羊及任何真实客户数据无关。
B21: 使用路径：打分卡（理解口径）→ 商家明细（看公式怎么算）→ 分层结果与业务动作（看结果怎么接业务）。

Sheet 字段字典与作业指引
B2: 字段字典（24个原始字段 + 1个合计公式列）
B4: 字段 | C4: 口径说明
B5: 商家ID / 商家名称 | C5: 商家唯一标识与虚构品牌名（脱敏模拟）
B6: 所属行业 | C6: 快消食品/美妆个护/消费电子/母婴/服饰/家居家装/医药健康/零售连锁
B7: 所在区域 / 客户来源 | C7: 华东等7大区；直客或渠道代理
B8: 签约时间 / 合作月数 | C8: 首次签约日期及至今月数
B9: 生命周期阶段 | C9: 潜客试用/首次订购客户/增购客户/续订客户/流失预警/已流失
B10: 合同类型 | C10: 订阅+消耗 或 纯消耗
B11: 近12月消耗-短信/AI外呼/Push及企微(元) | C11: 按通道拆分的近12个月消耗金额（消耗性收入）
B12: 近12月消耗合计(元) | C12: 三通道消耗合计（公式列） | D12: V(价值贡献）
B13: 月均发送量(万条) / 月均活跃发送天数(天) | C13: 触达量级与使用活跃度 | D13: A（活跃度）
B14: 触达场景数(个) | C14: 使用的触达场景数量（短信/卡片短信/外呼/Push/企微/Webhook，0-6）
B15: 数据接入深度(0-3级) | C15: 0未接入/1仅订单/2订单+行为/3全渠道一方数据
B16: 私域会员规模(万人) / 会员月活跃度(%) | C16: 商家可触达的会员资产规模与活跃水平 | D16: P(潜力）
B17: 营销团队人数(人) / 年度营销预算(万元) | C17: 商家营销组织与预算配置 | D17: P(潜力）
B18: 近12月大促参与次数(次) | C18: 618/双11/年货节等平台大促的参与次数 | D18: P(潜力）
B19: 续费次数(次) | C19: 历史续费次数 | D19: H(健康度）
B20: 近3月消耗环比趋势 | C20: 上升/持平/下降/连续下降 | D20: H(健康度）
B21: 是否战略客户 | C21: 总部签约的战略客户（分层时需业务校准）
B22: 年度营销预算(万元) | D22: P(潜力） | E22: 可拓展预算空间 = 年度营销预算 − 近 12 月消耗
B24: 四种分层方法 · 练习取数指引
B25: 分层方法 | C25: 建议取数字段 | D25: 练习要点
B26: 01 单一指标分层 | C26: 近12月消耗合计（M列） | D26: 对齐课件短信案例：用Excel直方图看消耗分布→自定阈值切出SKA/KA/腰部/基础/未激活→验证金字塔结构
B27: 02 四象限法 | C27: 价值轴：合计消耗、场景数、接入深度；潜力轴：会员规模、预算、团队、大促次数 | D27: 分别给两轴定义高/低档→四象限落位（核心经营/成熟守护/培育成长/自助长尾）→逐象限出策略；注意新签<3个月商家看潜力不看消耗
B28: 03 客户生命周期 | C28: 生命周期阶段（H列）+ 近3月趋势（X列）+ 合作月数（G列） | D28: 按潜客/首购/增购/续订/流失分层→各阶段核心目标与运营动作→找出流失预警名单
B29: 04 综合打分制 | C29: 自选4-6个维度（建议：消耗、活跃天数、场景数、接入深度、会员规模、大促次数） | D29: 自行设定权重与档位打分规则→加权得出综合分→按分数段切层→说明设计理由
B31: 提示：数据中刻意埋了『高潜新签』（低消耗高潜力）与『衰退KA』（连续下降）两类典型商家，适合用来讨论四象限与升降级规则。

Sheet 打分卡
B2: 商家分层打分卡（指标体系 · 权重 · 分档口径）
B3: 权重逻辑：结果指标定层级（价值40+活跃20），先行指标定倾斜（潜力30），风险指标管降级（健康10）。档界锚定有消耗商家的P25/P50/P75/P90分位数。
B6: 一级维度 | C6: 子指标 | D6: 子权重 | E6: 单位 | F6: 档界1 | G6: 档界2 | H6: 档界3 | I6: 档界4 | J6: 档界5 | K6: 1分 | L6: 2分 | M6: 3分 | N6: 4分 | O6: 5分
B7: 价值贡献 | C7: 近12月消耗合计 | D7: 25 | E7: 元 | F7: 0 | G7: 24000 | H7: 94000 | I7: 220000 | J7: 530000 | K7: 1 | L7: 2 | M7: 3 | N7: 4 | O7: 5
B8: 价值贡献 | C8: 触达场景数 | D8: 8 | E8: 个 | F8: 1 | G8: 2 | H8: 3 | I8: 4 | J8: 5 | K8: 1 | L8: 2 | M8: 3 | N8: 4 | O8: 5
B9: 价值贡献 | C9: 数据接入深度 | D9: 7 | E9: 级 | F9: 0 | G9: 1 | H9: 2 | I9: 3 | K9: 1 | L9: 2 | M9: 3 | N9: 5
B10: 使用活跃 | C10: 月均发送量 | D10: 10 | E10: 万条 | F10: 0 | G10: 2.5 | H10: 9.8 | I10: 24 | J10: 56 | K10: 1 | L10: 2 | M10: 3 | N10: 4 | O10: 5
B11: 使用活跃 | C11: 月均活跃发送天数 | D11: 10 | E11: 天 | F11: 0 | G11: 3 | H11: 5 | I11: 9 | J11: 15 | K11: 1 | L11: 2 | M11: 3 | N11: 4 | O11: 5
B12: 增长潜力 | C12: 私域会员规模 | D12: 12 | E12: 万人 | F12: 0 | G12: 2.8 | H12: 10.5 | I12: 33 | J12: 69 | K12: 1 | L12: 2 | M12: 3 | N12: 4 | O12: 5
B13: 增长潜力 | C13: 年度营销预算 | D13: 8 | E13: 万元 | F13: 0 | G13: 18 | H13: 39 | I13: 82 | J13: 192 | K13: 1 | L13: 2 | M13: 3 | N13: 4 | O13: 5
B14: 增长潜力 | C14: 近12月大促参与次数 | D14: 6 | E14: 次 | F14: 0 | G14: 1 | H14: 2 | I14: 3 | J14: 5 | K14: 1 | L14: 2 | M14: 3 | N14: 4 | O14: 5
B15: 增长潜力 | C15: 营销团队人数 | D15: 4 | E15: 人 | F15: 0 | G15: 1 | H15: 3 | I15: 6 | J15: 11 | K15: 1 | L15: 2 | M15: 3 | N15: 4 | O15: 5
B16: 健康度 | C16: 近3月消耗环比趋势 | D16: 6 | E16: 文本 | F16: 连续下降=1分 / 下降=2分 / 持平=3分 / 上升=5分（文本映射） | K16: 1 | L16: 2 | M16: 3 | O16: 5
B17: 健康度 | C17: 续费次数 | D17: 4 | E17: 次 | F17: 0 | G17: 1 | H17: 2 | K17: 1 | L17: 3 | M17: 5
B20: 分层映射规则
B21: SKA | C21: 综合分 ≥ 90
B22: KA | C22: 75 ≤ 综合分 < 90
B23: 腰部 | C23: 40 ≤ 综合分 < 75
B24: 基础长尾 | C24: 综合分 < 40（有消耗）
B25: 新客观察期 | C25: 消耗=0 且 合作月数<3（高潜新签培育池）
B26: 未激活 | C26: 消耗=0 且 合作月数≥3（沉默/流失池）
B28: 计算口径
B29: ① 维度分 = Σ(子权重 × 档位分) ÷ 5，折算为：价值分0-40、活跃分0-20、潜力分0-30、健康分0-10
B30: ② 综合分 = 价值分 + 活跃分 + 潜力分 + 健康分（百分制）
B31: ③ 新客修正：合作月数<3个月的商家，价值分按 潜力分÷30×40 折算（看潜力不看消耗）
B32: ④ 一票否决：近12月消耗=0 不参与评分分层，按合作月数分流至新客观察期/未激活
B33: ⑤ 预警规则：近3月趋势=连续下降 → 打「连续下降-预警」标签，运营优先介入
B34: ⑥ 迭代节奏：月度监测趋势，季度重算综合分，连续2个周期跨档才执行升降级

Sheet 商家明细
A1: 商家ID | B1: 商家名称 | C1: 所属行业 | D1: 所在区域 | E1: 客户来源 | F1: 签约时间 | G1: 合作月数 | H1: 生命周期阶段 | I1: 合同类型 | J1: 近12月消耗-短信(元) | K1: 近12月消耗-AI外呼(元) | L1: 近12月消耗-Push及企微(元) | M1: 近12月消耗合计(元) | N1: 消耗金额% | O1: 累计消耗金额 | P1: 累计消耗金额% | Q1: 月均发送量(万条) | R1: 月均活跃发送天数(天) | S1: 触达场景数(个) | T1: 数据接入深度(0-3级) | U1: 私域会员规模(万人) | V1: 会员月活跃度(%) | W1: 营销团队人数(人) | X1: 年度营销预算(万元) | Y1: 近12月大促参与次数(次) | Z1: 续费次数(次) | AA1: 近3月消耗环比趋势 | AB1: 是否战略客户 | AC1: 消耗档位分 | AD1: 场景档位分 | AE1: 深度档位分 | AF1: 发送量档位分 | AG1: 天数档位分 | AH1: 会员档位分 | AI1: 预算档位分 | AJ1: 大促档位分 | AK1: 团队档位分 | AL1: 趋势档位分 | AM1: 续费档位分 | AN1: 价值分(0-40) | AO1: 活跃分(0-20) | AP1: 潜力分(0-30) | AQ1: 健康分(0-10) | AR1: 综合分 | AS1: 分层结果 | AT1: 预警标签 | AU1: 主打通道策略
A2: QA00001 | B2: 素珂香氛 | C2: 美妆个护 | D2: 西北 | E2: 直客 | F2: 2024-04-10 | G2: 26 | H2: 续订客户 | I2: 订阅+消耗 | J2: 4377900 | K2: 1659700 | L2: 1830900 | M2: =SUM(J2:L2) -> 7868500 | N2: =M2/$M$2002 -> 0.041251712 | O2: =SUM($M$2:M2) -> 7868500 | P2: =O2/$M$2002 -> 0.041251712 | Q2: 804.3 | R2: 25 | S2: 5 | T2: 3 | U2: 808.3 | V2: 29 | W2: 31 | X2: 4761 | Y2: 10 | Z2: 2 | AA2: 持平 | AB2: 是 | AC2: =IFERROR(LOOKUP(M2,打分卡!$F$7:$J$7,打分卡!$K$7:$O$7),1) -> 5 | AD2: =IFERROR(LOOKUP(S2,打分卡!$F$8:$J$8,打分卡!$K$8:$O$8),1) -> 5 | AE2: =IFERROR(LOOKUP(T2,打分卡!$F$9:$I$9,打分卡!$K$9:$N$9),1) -> 5 | AF2: =IFERROR(LOOKUP(Q2,打分卡!$F$10:$J$10,打分卡!$K$10:$O$10),1) -> 5 | AG2: =IFERROR(LOOKUP(R2,打分卡!$F$11:$J$11,打分卡!$K$11:$O$11),1) -> 5 | AH2: =IFERROR(LOOKUP(U2,打分卡!$F$12:$J$12,打分卡!$K$12:$O$12),1) -> 5 | AI2: =IFERROR(LOOKUP(X2,打分卡!$F$13:$J$13,打分卡!$K$13:$O$13),1) -> 5 | AJ2: =IFERROR(LOOKUP(Y2,打分卡!$F$14:$J$14,打分卡!$K$14:$O$14),1) -> 5 | AK2: =IFERROR(LOOKUP(W2,打分卡!$F$15:$J$15,打分卡!$K$15:$O$15),1) -> 5 | AL2: =IF(AA2="连续下降",1,IF(AA2="下降",2,IF(AA2="上升",5,3))) -> 3 | AM2: =IFERROR(LOOKUP(Z2,打分卡!$F$17:$H$17,打分卡!$K$17:$M$17),1) -> 5 | AN2: =(打分卡!$D$7*AC2+打分卡!$D$8*AD2+打分卡!$D$9*AE2)/5 -> 40 | AO2: =(打分卡!$D$10*AF2+打分卡!$D$11*AG2)/5 -> 20 | AP2: =(打分卡!$D$12*AH2+打分卡!$D$13*AI2+打分卡!$D$14*AJ2+打分卡!$D$15*AK2)/5 -> 30 | AQ2: =(打分卡!$D$16*AL2+打分卡!$D$17*AM2)/5 -> 7.6 | AR2: =IF(G2<3,AP2/30*40+AO2+AP2+AQ2,AN2+AO2+AP2+AQ2) -> 97.6 | AS2: =IF(M2=0,IF(G2<3,"新客观察期","未激活"),IF(AR2>=90,"SKA",IF(AR2>=75,"KA",IF(AR2>=40,"腰部","基础长尾")))) -> SKA | AT2: =IF(AA2="连续下降","连续下降-预警","") | AU2: =IF(AS2="SKA","守·共创：卡片短信/AI外呼新场景POC",IF(AS2="KA","扩·深化：AI外呼场景深化+Push/企微补全",IF(AS2="腰部","拉·主攻：主推AI外呼+大促作战包",IF(AS2="新客观察期","培育：入门包+1v1场景教育",IF(AS2="基础长尾","激活：企微+Push低成本先跑","唤醒：短信模板+首充补贴"))))) -> 守·共创：卡片短信/AI外呼新场景POC
A3: QA00002 | B3: 海刻零食 | C3: 快消食品 | D3: 华中 | E3: 直客 | F3: 2023-07-22 | G3: 35 | H3: 增购客户 | I3: 订阅+消耗 | J3: 3514300 | K3: 2415200 | L3: 875200 | M3: =SUM(J3:L3) -> 6804700 | N3: =M3/$M$2002 -> 0.035674591 | O3: =SUM($M$2:M3) -> 14673200 | P3: =O3/$M$2002 -> 0.076926303 | Q3: 753.5 | R3: 20 | S3: 5 | T3: 3 | U3: 1929.9 | V3: 31 | W3: 43 | X3: 4069 | Y3: 7 | Z3: 3 | AA3: 持平 | AB3: 是 | AC3: =IFERROR(LOOKUP(M3,打分卡!$F$7:$J$7,打分卡!$K$7:$O$7),1) -> 5 | AD3: =IFERROR(LOOKUP(S3,打分卡!$F$8:$J$8,打分卡!$K$8:$O$8),1) -> 5 | AE3: =IFERROR(LOOKUP(T3,打分卡!$F$9:$I$9,打分卡!$K$9:$N$9),1) -> 5 | AF3: =IFERROR(LOOKUP(Q3,打分卡!$F$10:$J$10,打分卡!$K$10:$O$10),1) -> 5 | AG3: =IFERROR(LOOKUP(R3,打分卡!$F$11:$J$11,打分卡!$K$11:$O$11),1) -> 5 | AH3: =IFERROR(LOOKUP(U3,打分卡!$F$12:$J$12,打分卡!$K$12:$O$12),1) -> 5 | AI3: =IFERROR(LOOKUP(X3,打分卡!$F$13:$J$13,打分卡!$K$13:$O$13),1) -> 5 | AJ3: =IFERROR(LOOKUP(Y3,打分卡!$F$14:$J$14,打分卡!$K$14:$O$14),1) -> 5 | AK3: =IFERROR(LOOKUP(W3,打分卡!$F$15:$J$15,打分卡!$K$15:$O$15),1) -> 5 | AL3: =IF(AA3="连续下降",1,IF(AA3="下降",2,IF(AA3="上升",5,3))) -> 3 | AM3: =IFERROR(LOOKUP(Z3,打分卡!$F$17:$H$17,打分卡!$K$17:$M$17),1) -> 5 | AN3: =(打分卡!$D$7*AC3+打分卡!$D$8*AD3+打分卡!$D$9*AE3)/5 -> 40 | AO3: =(打分卡!$D$10*AF3+打分卡!$D$11*AG3)/5 -> 20 | AP3: =(打分卡!$D$12*AH3+打分卡!$D$13*AI3+打分卡!$D$14*AJ3+打分卡!$D$15*AK3)/5 -> 30 | AQ3: =(打分卡!$D$16*AL3+打分卡!$D$17*AM3)/5 -> 7.6 | AR3: =IF(G3<3,AP3/30*40+AO3+AP3+AQ3,AN3+AO3+AP3+AQ3) -> 97.6 | AS3: =IF(M3=0,IF(G3<3,"新客观察期","未激活"),IF(AR3>=90,"SKA",IF(AR3>=75,"KA",IF(AR3>=40,"腰部","基础长尾")))) -> SKA | AT3: =IF(AA3="连续下降","连续下降-预警","") | AU3: =IF(AS3="SKA","守·共创：卡片短信/AI外呼新场景POC",IF(AS3="KA","扩·深化：AI外呼场景深化+Push/企微补全",IF(AS3="腰部","拉·主攻：主推AI外呼+大促作战包",IF(AS3="新客观察期","培育：入门包+1v1场景教育",IF(AS3="基础长尾","激活：企微+Push低成本先跑","唤醒：短信模板+首充补贴"))))) -> 守·共创：卡片短信/AI外呼新场景POC
A4: QA00003 | B4: 沐之家居 | C4: 家居家装 | D4: 华南 | E4: 渠道代理 | F4: 2023-01-29 | G4: 41 | H4: 续订客户 | I4: 订阅+消耗 | J4: 3838200 | K4: 1821100 | L4: 297900 | M4: =SUM(J4:L4) -> 5957200 | N4: =M4/$M$2002 -> 0.031231454 | O4: =SUM($M$2:M4) -> 20630400 | P4: =O4/$M$2002 -> 0.10815776 | Q4: 744.7 | R4: 22 | S4: 5 | T4: 3 | U4: 1807.9 | V4: 32 | W4: 40 | X4: 8890 | Y4: 9 | Z4: 4 | AA4: 上升 | AB4: 是 | AC4: =IFERROR(LOOKUP(M4,打分卡!$F$7:$J$7,打分卡!$K$7:$O$7),1) -> 5 | AD4: =IFERROR(LOOKUP(S4,打分卡!$F$8:$J$8,打分卡!$K$8:$O$8),1) -> 5 | AE4: =IFERROR(LOOKUP(T4,打分卡!$F$9:$I$9,打分卡!$K$9:$N$9),1) -> 5 | AF4: =IFERROR(LOOKUP(Q4,打分卡!$F$10:$J$10,打分卡!$K$10:$O$10),1) -> 5 | AG4: =IFERROR(LOOKUP(R4,打分卡!$F$11:$J$11,打分卡!$K$11:$O$11),1) -> 5 | AH4: =IFERROR(LOOKUP(U4,打分卡!$F$12:$J$12,打分卡!$K$12:$O$12),1) -> 5 | AI4: =IFERROR(LOOKUP(X4,打分卡!$F$13:$J$13,打分卡!$K$13:$O$13),1) -> 5 | AJ4: =IFERROR(LOOKUP(Y4,打分卡!$F$14:$J$14,打分卡!$K$14:$O$14),1) -> 5 | AK4: =IFERROR(LOOKUP(W4,打分卡!$F$15:$J$15,打分卡!$K$15:$O$15),1) -> 5 | AL4: =IF(AA4="连续下降",1,IF(AA4="下降",2,IF(AA4="上升",5,3))) -> 5 | AM4: =IFERROR(LOOKUP(Z4,打分卡!$F$17:$H$17,打分卡!$K$17:$M$17),1) -> 5 | AN4: =(打分卡!$D$7*AC4+打分卡!$D$8*AD4+打分卡!$D$9*AE4)/5 -> 40 | AO4: =(打分卡!$D$10*AF4+打分卡!$D$11*AG4)/5 -> 20 | AP4: =(打分卡!$D$12*AH4+打分卡!$D$13*AI4+打分卡!$D$14*AJ4+打分卡!$D$15*AK4)/5 -> 30 | AQ4: =(打分卡!$D$16*AL4+打分卡!$D$17*AM4)/5 -> 10 | AR4: =IF(G4<3,AP4/30*40+AO4+AP4+AQ4,AN4+AO4+AP4+AQ4) -> 100 | AS4: =IF(M4=0,IF(G4<3,"新客观察期","未激活"),IF(AR4>=90,"SKA",IF(AR4>=75,"KA",IF(AR4>=40,"腰部","基础长尾")))) -> SKA | AT4: =IF(AA4="连续下降","连续下降-预警","") | AU4: =IF(AS4="SKA","守·共创：卡片短信/AI外呼新场景POC",IF(AS4="KA","扩·深化：AI外呼场景深化+Push/企微补全",IF(AS4="腰部","拉·主攻：主推AI外呼+大促作战包",IF(AS4="新客观察期","培育：入门包+1v1场景教育",IF(AS4="基础长尾","激活：企微+Push低成本先跑","唤醒：短信模板+首充补贴"))))) -> 守·共创：卡片短信/AI外呼新场景POC
A5: QA00004 | B5: 森橙烘焙 | C5: 快消食品 | D5: 华东 | E5: 渠道代理 | F5: 2022-09-30 | G5: 45 | H5: 增购客户 | I5: 订阅+消耗 | J5: 3011800 | K5: 1336600 | L5: 1210900 | M5: =SUM(J5:L5) -> 5559300 | N5: =M5/$M$2002 -> 0.029145408 | O5: =SUM($M$2:M5) -> 26189700 | P5: =O5/$M$2002 -> 0.13730317 | Q5: 604.6 | R5: 22 | S5: 5 | T5: 3 | U5: 2528.8 | V5: 26 | W5: 42 | X5: 3015 | Y5: 9 | Z5: 4 | AA5: 持平 | AB5: 是 | AC5: =IFERROR(LOOKUP(M5,打分卡!$F$7:$J$7,打分卡!$K$7:$O$7),1) -> 5 | AD5: =IFERROR(LOOKUP(S5,打分卡!$F$8:$J$8,打分卡!$K$8:$O$8),1) -> 5 | AE5: =IFERROR(LOOKUP(T5,打分卡!$F$9:$I$9,打分卡!$K$9:$N$9),1) -> 5 | AF5: =IFERROR(LOOKUP(Q5,打分卡!$F$10:$J$10,打分卡!$K$10:$O$10),1) -> 5 | AG5: =IFERROR(LOOKUP(R5,打分卡!$F$11:$J$11,打分卡!$K$11:$O$11),1) -> 5 | AH5: =IFERROR(LOOKUP(U5,打分卡!$F$12:$J$12,打分卡!$K$12:$O$12),1) -> 5 | AI5: =IFERROR(LOOKUP(X5,打分卡!$F$13:$J$13,打分卡!$K$13:$O$13),1) -> 5 | AJ5: =IFERROR(LOOKUP(Y5,打分卡!$F$14:$J$14,打分卡!$K$14:$O$14),1) -> 5 | AK5: =IFERROR(LOOKUP(W5,打分卡!$F$15:$J$15,打分卡!$K$15:$O$15),1) -> 5 | AL5: =IF(AA5="连续下降",1,IF(AA5="下降",2,IF(AA5="上升",5,3))) -> 3 | AM5: =IFERROR(LOOKUP(Z5,打分卡!$F$17:$H$17,打分卡!$K$17:$M$17),1) -> 5 | AN5: =(打分卡!$D$7*AC5+打分卡!$D$8*AD5+打分卡!$D$9*AE5)/5 -> 40 | AO5: =(打分卡!$D$10*AF5+打分卡!$D$11*AG5)/5 -> 20 | AP5: =(打分卡!$D$12*AH5+打分卡!$D$13*AI5+打分卡!$D$14*AJ5+打分卡!$D$15*AK5)/5 -> 30 | AQ5: =(打分卡!$D$16*AL5+打分卡!$D$17*AM5)/5 -> 7.6 | AR5: =IF(G5<3,AP5/30*40+AO5+AP5+AQ5,AN5+AO5+AP5+AQ5) -> 97.6 | AS5: =IF(M5=0,IF(G5<3,"新客观察期","未激活"),IF(AR5>=90,"SKA",IF(AR5>=75,"KA",IF(AR5>=40,"腰部","基础长尾")))) -> SKA | AT5: =IF(AA5="连续下降","连续下降-预警","") | AU5: =IF(AS5="SKA","守·共创：卡片短信/AI外呼新场景POC",IF(AS5="KA","扩·深化：AI外呼场景深化+Push/企微补全",IF(AS5="腰部","拉·主攻：主推AI外呼+大促作战包",IF(AS5="新客观察期","培育：入门包+1v1场景教育",IF(AS5="基础长尾","激活：企微+Push低成本先跑","唤醒：短信模板+首充补贴"))))) -> 守·共创：卡片短信/AI外呼新场景POC
A6: QA00005 | B6: 鹿棠食品 | C6: 快消食品 | D6: 华东 | E6: 直客 | F6: 2023-09-17 | G6: 33 | H6: 增购客户 | I6: 订阅+消耗 | J6: 2838900 | K6: 1444000 | L6: 366600 | M6: =SUM(J6:L6) -> 4649500 | N6: =M6/$M$2002 -> 0.024375654 | O6: =SUM($M$2:M6) -> 30839200 | P6: =O6/$M$2002 -> 0.16167882 | Q6: 446.1 | R6: 25 | S6: 3 | T6: 2 | U6: 1190.1 | V6: 35 | W6: 15 | X6: 1641 | Y6: 8 | Z6: 3 | AA6: 上升 | AB6: 是 | AC6: =IFERROR(LOOKUP(M6,打分卡!$F$7:$J$7,打分卡!$K$7:$O$7),1) -> 5 | AD6: =IFERROR(LOOKUP(S6,打分卡!$F$8:$J$8,打分卡!$K$8:$O$8),1) -> 3 | AE6: =IFERROR(LOOKUP(T6,打分卡!$F$9:$I$9,打分卡!$K$9:$N$9),1) -> 3 | AF6: =IFERROR(LOOKUP(Q6,打分卡!$F$10:$J$10,打分卡!$K$10:$O$10),1) -> 5 | AG6: =IFERROR(LOOKUP(R6,打分卡!$F$11:$J$11,打分卡!$K$11:$O$11),1) -> 5 | AH6: =IFERROR(LOOKUP(U6,打分卡!$F$12:$J$12,打分卡!$K$12:$O$12),1) -> 5 | AI6: =IFERROR(LOOKUP(X6,打分卡!$F$13:$J$13,打分卡!$K$13:$O$13),1) -> 5 | AJ6: =IFERROR(LOOKUP(Y6,打分卡!$F$14:$J$14,打分卡!$K$14:$O$14),1) -> 5 | AK6: =IFERROR(LOOKUP(W6,打分卡!$F$15:$J$15,打分卡!$K$15:$O$15),1) -> 5 | AL6: =IF(AA6="连续下降",1,IF(AA6="下降",2,IF(AA6="上升",5,3))) -> 5 | AM6: =IFERROR(LOOKUP(Z6,打分卡!$F$17:$H$17,打分卡!$K$17:$M$17),1) -> 5 | AN6: =(打分卡!$D$7*AC6+打分卡!$D$8*AD6+打分卡!$D$9*AE6)/5 -> 34 | AO6: =(打分卡!$D$10*AF6+打分卡!$D$11*AG6)/5 -> 20 | AP6: =(打分卡!$D$12*AH6+打分卡!$D$13*AI6+打分卡!$D$14*AJ6+打分卡!$D$15*AK6)/5 -> 30 | AQ6: =(打分卡!$D$16*AL6+打分卡!$D$17*AM6)/5 -> 10 | AR6: =IF(G6<3,AP6/30*40+AO6+AP6+AQ6,AN6+AO6+AP6+AQ6) -> 94 | AS6: =IF(M6=0,IF(G6<3,"新客观察期","未激活"),IF(AR6>=90,"SKA",IF(AR6>=75,"KA",IF(AR6>=40,"腰部","基础长尾")))) -> SKA | AT6: =IF(AA6="连续下降","连续下降-预警","") | AU6: =IF(AS6="SKA","守·共创：卡片短信/AI外呼新场景POC",IF(AS6="KA","扩·深化：AI外呼场景深化+Push/企微补全",IF(AS6="腰部","拉·主攻：主推AI外呼+大促作战包",IF(AS6="新客观察期","培育：入门包+1v1场景教育",IF(AS6="基础长尾","激活：企微+Push低成本先跑","唤醒：短信模板+首充补贴"))))) -> 守·共创：卡片短信/AI外呼新场景POC
A7: QA00006 | B7: 屿岚康养 | C7: 医药健康 | D7: 华中 | E7: 直客 | F7: 2023-09-21 | G7: 33 | H7: 流失预警 | I7: 订阅+消耗 | J7: 1802900 | K7: 1350400 | L7: 504300 | M7: =SUM(J7:L7) -> 3657600 | N7: =M7/$M$2002 -> 0.01917548 | O7: =SUM($M$2:M7) -> 34496800 | P7: =O7/$M$2002 -> 0.1808543 | Q7: 331.7 | R7: 17 | S7: 4 | T7: 3 | U7: 199.1 | V7: 39 | W7: 15 | X7: 1633 | Y7: 1 | Z7: 2 | AA7: 连续下降 | AB7: 是 | AC7: =IFERROR(LOOKUP(M7,打分卡!$F$7:$J$7,打分卡!$K$7:$O$7),1) -> 5 | AD7: =IFERROR(LOOKUP(S7,打分卡!$F$8:$J$8,打分卡!$K$8:$O$8),1) -> 4 | AE7: =IFERROR(LOOKUP(T7,打分卡!$F$9:$I$9,打分卡!$K$9:$N$9),1) -> 5 | AF7: =IFERROR(LOOKUP(Q7,打分卡!$F$10:$J$10,打分卡!$K$10:$O$10),1) -> 5 | AG7: =IFERROR(LOOKUP(R7,打分卡!$F$11:$J$11,打分卡!$K$11:$O$11),1) -> 5 | AH7: =IFERROR(LOOKUP(U7,打分卡!$F$12:$J$12,打分卡!$K$12:$O$12),1) -> 5 | AI7: =IFERROR(LOOKUP(X7,打分卡!$F$13:$J$13,打分卡!$K$13:$O$13),1) -> 5 | AJ7: =IFERROR(LOOKUP(Y7,打分卡!$F$14:$J$14,打分卡!$K$14:$O$14),1) -> 2 | AK7: =IFERROR(LOOKUP(W7,打分卡!$F$15:$J$15,打分卡!$K$15:$O$15),1) -> 5 | AL7: =IF(AA7="连续下降",1,IF(AA7="下降",2,IF(AA7="上升",5,3))) -> 1 | AM7: =IFERROR(LOOKUP(Z7,打分卡!$F$17:$H$17,打分卡!$K$17:$M$17),1) -> 5 | AN7: =(打分卡!$D$7*AC7+打分卡!$D$8*AD7+打分卡!$D$9*AE7)/5 -> 38.4 | AO7: =(打分卡!$D$10*AF7+打分卡!$D$11*AG7)/5 -> 20 | AP7: =(打分卡!$D$12*AH7+打分卡!$D$13*AI7+打分卡!$D$14*AJ7+打分卡!$D$15*AK7)/5 -> 26.4 | AQ7: =(打分卡!$D$16*AL7+打分卡!$D$17*AM7)/5 -> 5.2 | AR7: =IF(G7<3,AP7/30*40+AO7+AP7+AQ7,AN7+AO7+AP7+AQ7) -> 90 | AS7: =IF(M7=0,IF(G7<3,"新客观察期","未激活"),IF(AR7>=90,"SKA",IF(AR7>=75,"KA",IF(AR7>=40,"腰部","基础长尾")))) -> SKA | AT7: =IF(AA7="连续下降","连续下降-预警","") -> 连续下降-预警 | AU7: =IF(AS7="SKA","守·共创：卡片短信/AI外呼新场景POC",IF(AS7="KA","扩·深化：AI外呼场景深化+Push/企微补全",IF(AS7="腰部","拉·主攻：主推AI外呼+大促作战包",IF(AS7="新客观察期","培育：入门包+1v1场景教育",IF(AS7="基础长尾","激活：企微+Push低成本先跑","唤醒：短信模板+首充补贴"))))) -> 守·共创：卡片短信/AI外呼新场景POC
A8: QA00007 | B8: 安溪美妆 | C8: 美妆个护 | D8: 华东 | E8: 直客 | F8: 2025-04-19 | G8: 14 | H8: 增购客户 | I8: 订阅+消耗 | J8: 2277200 | K8: 934600 | L8: 429500 | M8: =SUM(J8:L8) -> 3641300 | N8: =M8/$M$2002 -> 0.019090025 | O8: =SUM($M$2:M8) -> 38138100 | P8: =O8/$M$2002 -> 0.19994432 | Q8: 361.4 | R8: 22 | S8: 4 | T8: 2 | U8: 675.7 | V8: 42 | W8: 8 | X8: 892 | Y8: 6 | Z8: 3 | AA8: 上升 | AB8: 是 | AC8: =IFERROR(LOOKUP(M8,打分卡!$F$7:$J$7,打分卡!$K$7:$O$7),1) -> 5 | AD8: =IFERROR(LOOKUP(S8,打分卡!$F$8:$J$8,打分卡!$K$8:$O$8),1) -> 4 | AE8: =IFERROR(LOOKUP(T8,打分卡!$F$9:$I$9,打分卡!$K$9:$N$9),1) -> 3 | AF8: =IFERROR(LOOKUP(Q8,打分卡!$F$10:$J$10,打分卡!$K$10:$O$10),1) -> 5 | AG8: =IFERROR(LOOKUP(R8,打分卡!$F$11:$J$11,打分卡!$K$11:$O$11),1) -> 5 | AH8: =IFERROR(LOOKUP(U8,打分卡!$F$12:$J$12,打分卡!$K$12:$O$12),1) -> 5 | AI8: =IFERROR(LOOKUP(X8,打分卡!$F$13:$J$13,打分卡!$K$13:$O$13),1) -> 5 | AJ8: =IFERROR(LOOKUP(Y8,打分卡!$F$14:$J$14,打分卡!$K$14:$O$14),1) -> 5 | AK8: =IFERROR(LOOKUP(W8,打分卡!$F$15:$J$15,打分卡!$K$15:$O$15),1) -> 4 | AL8: =IF(AA8="连续下降",1,IF(AA8="下降",2,IF(AA8="上升",5,3))) -> 5 | AM8: =IFERROR(LOOKUP(Z8,打分卡!$F$17:$H$17,打分卡!$K$17:$M$17),1) -> 5 | AN8: =(打分卡!$D$7*AC8+打分卡!$D$8*AD8+打分卡!$D$9*AE8)/5 -> 35.6 | AO8: =(打分卡!$D$10*AF8+打分卡!$D$11*AG8)/5 -> 20 | AP8: =(打分卡!$D$12*AH8+打分卡!$D$13*AI8+打分卡!$D$14*AJ8+打分卡!$D$15*AK8)/5 -> 29.2 | AQ8: =(打分卡!$D$16*AL8+打分卡!$D$17*AM8)/5 -> 10 | AR8: =IF(G8<3,AP8/30*40+AO8+AP8+AQ8,AN8+AO8+AP8+AQ8) -> 94.8 | AS8: =IF(M8=0,IF(G8<3,"新客观察期","未激活"),IF(AR8>=90,"SKA",IF(AR8>=75,"KA",IF(AR8>=40,"腰部","基础长尾")))) -> SKA | AT8: =IF(AA8="连续下降","连续下降-预警","") | AU8: =IF(AS8="SKA","守·共创：卡片短信/AI外呼新场景POC",IF(AS8="KA","扩·深化：AI外呼场景深化+Push/企微补全",IF(AS8="腰部","拉·主攻：主推AI外呼+大促作战包",IF(AS8="新客观察期","培育：入门包+1v1场景教育",IF(AS8="基础长尾","激活：企微+Push低成本先跑","唤醒：短信模板+首充补贴"))))) -> 守·共创：卡片短信/AI外呼新场景POC
A9: QA00008 | B9: 南棠衣品 | C9: 服饰 | D9: 华东 | E9: 直客 | F9: 2025-02-07 | G9: 16 | H9: 流失预警 | I9: 订阅+消耗 | J9: 1686200 | K9: 992100 | L9: 676000 | M9: =SUM(J9:L9) -> 3354300 | N9: =M9/$M$2002 -> 0.017585387 | O9: =SUM($M$2:M9) -> 41492400 | P9: =O9/$M$2002 -> 0.21752971 | Q9: 404.4 | R9: 20 | S9: 5 | T9: 2 | U9: 163.3 | V9: 24 | W9: 25 | X9: 1181 | Y9: 3 | Z9: 3 | AA9: 连续下降 | AB9: 否 | AC9: =IFERROR(LOOKUP(M9,打分卡!$F$7:$J$7,打分卡!$K$7:$O$7),1) -> 5 | AD9: =IFERROR(LOOKUP(S9,打分卡!$F$8:$J$8,打分卡!$K$8:$O$8),1) -> 5 | AE9: =IFERROR(LOOKUP(T9,打分卡!$F$9:$I$9,打分卡!$K$9:$N$9),1) -> 3 | AF9: =IFERROR(LOOKUP(Q9,打分卡!$F$10:$J$10,打分卡!$K$10:$O$10),1) -> 5 | AG9: =IFERROR(LOOKUP(R9,打分卡!$F$11:$J$11,打分卡!$K$11:$O$11),1) -> 5 | AH9: =IFERROR(LOOKUP(U9,打分卡!$F$12:$J$12,打分卡!$K$12:$O$12),1) -> 5 | AI9: =IFERROR(LOOKUP(X9,打分卡!$F$13:$J$13,打分卡!$K$13:$O$13),1) -> 5 | AJ9: =IFERROR(LOOKUP(Y9,打分卡!$F$14:$J$14,打分卡!$K$14:$O$14),1) -> 4 | AK9: =IFERROR(LOOKUP(W9,打分卡!$F$15:$J$15,打分卡!$K$15:$O$15),1) -> 5 | AL9: =IF(AA9="连续下降",1,IF(AA9="下降",2,IF(AA9="上升",5,3))) -> 1 | AM9: =IFERROR(LOOKUP(Z9,打分卡!$F$17:$H$17,打分卡!$K$17:$M$17),1) -> 5 | AN9: =(打分卡!$D$7*AC9+打分卡!$D$8*AD9+打分卡!$D$9*AE9)/5 -> 37.2 | AO9: =(打分卡!$D$10*AF9+打分卡!$D$11*AG9)/5 -> 20 | AP9: =(打分卡!$D$12*AH9+打分卡!$D$13*AI9+打分卡!$D$14*AJ9+打分卡!$D$15*AK9)/5 -> 28.8 | AQ9: =(打分卡!$D$16*AL9+打分卡!$D$17*AM9)/5 -> 5.2 | AR9: =IF(G9<3,AP9/30*40+AO9+AP9+AQ9,AN9+AO9+AP9+AQ9) -> 91.2 | AS9: =IF(M9=0,IF(G9<3,"新客观察期","未激活"),IF(AR9>=90,"SKA",IF(AR9>=75,"KA",IF(AR9>=40,"腰部","基础长尾")))) -> SKA | AT9: =IF(AA9="连续下降","连续下降-预警","") -> 连续下降-预警 | AU9: =IF(AS9="SKA","守·共创：卡片短信/AI外呼新场景POC",IF(AS9="KA","扩·深化：AI外呼场景深化+Push/企微补全",IF(AS9="腰部","拉·主攻：主推AI外呼+大促作战包",IF(AS9="新客观察期","培育：入门包+1v1场景教育",IF(AS9="基础长尾","激活：企微+Push低成本先跑","唤醒：短信模板+首充补贴"))))) -> 守·共创：卡片短信/AI外呼新场景POC
A10: QA00009 | B10: 沁茉母婴 | C10: 母婴 | D10: 华东 | E10: 直客 | F10: 2024-11-19 | G10: 19 | H10: 续订客户 | I10: 订阅+消耗 | J10: 1980500 | K10: 686000 | L10: 389300 | M10: =SUM(J10:L10) -> 3055800 | N10: =M10/$M$2002 -> 0.016020459 | O10: =SUM($M$2:M10) -> 44548200 | P10: =O10/$M$2002 -> 0.23355017 | Q10: 415.5 | R10: 13 | S10: 3 | T10: 2 | U10: 1462.6 | V10: 49 | W10: 6 | X10: 1026 | Y10: 6 | Z10: 2 | AA10: 持平 | AB10: 否 | AC10: =IFERROR(LOOKUP(M10,打分卡!$F$7:$J$7,打分卡!$K$7:$O$7),1) -> 5 | AD10: =IFERROR(LOOKUP(S10,打分卡!$F$8:$J$8,打分卡!$K$8:$O$8),1) -> 3 | AE10: =IFERROR(LOOKUP(T10,打分卡!$F$9:$I$9,打分卡!$K$9:$N$9),1) -> 3 | AF10: =IFERROR(LOOKUP(Q10,打分卡!$F$10:$J$10,打分卡!$K$10:$O$10),1) -> 5 | AG10: =IFERROR(LOOKUP(R10,打分卡!$F$11:$J$11,打分卡!$K$11:$O$11),1) -> 4 | AH10: =IFERROR(LOOKUP(U10,打分卡!$F$12:$J$12,打分卡!$K$12:$O$12),1) -> 5 | AI10: =IFERROR(LOOKUP(X10,打分卡!$F$13:$J$13,打分卡!$K$13:$O$13),1) -> 5 | AJ10: =IFERROR(LOOKUP(Y10,打分卡!$F$14:$J$14,打分卡!$K$14:$O$14),1) -> 5 | AK10: =IFERROR(LOOKUP(W10,打分卡!$F$15:$J$15,打分卡!$K$15:$O$15),1) -> 4 | AL10: =IF(AA10="连续下降",1,IF(AA10="下降",2,IF(AA10="上升",5,3))) -> 3 | AM10: =IFERROR(LOOKUP(Z10,打分卡!$F$17:$H$17,打分卡!$K$17:$M$17),1) -> 5 | AN10: =(打分卡!$D$7*AC10+打分卡!$D$8*AD10+打分卡!$D$9*AE10)/5 -> 34 | AO10: =(打分卡!$D$10*AF10+打分卡!$D$11*AG10)/5 -> 18 | AP10: =(打分卡!$D$12*AH10+打分卡!$D$13*AI10+打分卡!$D$14*AJ10+打分卡!$D$15*AK10)/5 -> 29.2 | AQ10: =(打分卡!$D$16*AL10+打分卡!$D$17*AM10)/5 -> 7.6 | AR10: =IF(G10<3,AP10/30*40+AO10+AP10+AQ10,AN10+AO10+AP10+AQ10) -> 88.8 | AS10: =IF(M10=0,IF(G10<3,"新客观察期","未激活"),IF(AR10>=90,"SKA",IF(AR10>=75,"KA",IF(AR10>=40,"腰部","基础长尾")))) -> KA | AT10: =IF(AA10="连续下降","连续下降-预警","") | AU10: =IF(AS10="SKA","守·共创：卡片短信/AI外呼新场景POC",IF(AS10="KA","扩·深化：AI外呼场景深化+Push/企微补全",IF(AS10="腰部","拉·主攻：主推AI外呼+大促作战包",IF(AS10="新客观察期","培育：入门包+1v1场景教育",IF(AS10="基础长尾","激活：企微+Push低成本先跑","唤醒：短信模板+首充补贴"))))) -> 扩·深化：AI外呼场景深化+Push/企微补全
A11: QA00010 | B11: 柚野母婴 | C11: 母婴 | D11: 华北 | E11: 渠道代理 | F11: 2024-06-01 | G11: 25 | H11: 增购客户 | I11: 订阅+消耗 | J11: 1763700 | K11: 818600 | L11: 307200 | M11: =SUM(J11:L11) -> 2889500 | N11: =M11/$M$2002 -> 0.015148608 | O11: =SUM($M$2:M11) -> 47437700 | P11: =O11/$M$2002 -> 0.24869878 | Q11: 308.9 | R11: 19 | S11: 5 | T11: 2 | U11: 586.5 | V11: 45 | W11: 17 | X11: 1005 | Y11: 6 | Z11: 1 | AA11: 持平 | AB11: 否 | AC11: =IFERROR(LOOKUP(M11,打分卡!$F$7:$J$7,打分卡!$K$7:$O$7),1) -> 5 | AD11: =IFERROR(LOOKUP(S11,打分卡!$F$8:$J$8,打分卡!$K$8:$O$8),1) -> 5 | AE11: =IFERROR(LOOKUP(T11,打分卡!$F$9:$I$9,打分卡!$K$9:$N$9),1) -> 3 | AF11: =IFERROR(LOOKUP(Q11,打分卡!$F$10:$J$10,打分卡!$K$10:$O$10),1) -> 5 | AG11: =IFERROR(LOOKUP(R11,打分卡!$F$11:$J$11,打分卡!$K$11:$O$11),1) -> 5 | AH11: =IFERROR(LOOKUP(U11,打分卡!$F$12:$J$12,打分卡!$K$12:$O$12),1) -> 5 | AI11: =IFERROR(LOOKUP(X11,打分卡!$F$13:$J$13,打分卡!$K$13:$O$13),1) -> 5 | AJ11: =IFERROR(LOOKUP(Y11,打分卡!$F$14:$J$14,打分卡!$K$14:$O$14),1) -> 5 | AK11: =IFERROR(LOOKUP(W11,打分卡!$F$15:$J$15,打分卡!$K$15:$O$15),1) -> 5 | AL11: =IF(AA11="连续下降",1,IF(AA11="下降",2,IF(AA11="上升",5,3))) -> 3 | AM11: =IFERROR(LOOKUP(Z11,打分卡!$F$17:$H$17,打分卡!$K$17:$M$17),1) -> 3 | AN11: =(打分卡!$D$7*AC11+打分卡!$D$8*AD11+打分卡!$D$9*AE11)/5 -> 37.2 | AO11: =(打分卡!$D$10*AF11+打分卡!$D$11*AG11)/5 -> 20 | AP11: =(打分卡!$D$12*AH11+打分卡!$D$13*AI11+打分卡!$D$14*AJ11+打分卡!$D$15*AK11)/5 -> 30 | AQ11: =(打分卡!$D$16*AL11+打分卡!$D$17*AM11)/5 -> 6 | AR11: =IF(G11<3,AP11/30*40+AO11+AP11+AQ11,AN11+AO11+AP11+AQ11) -> 93.2 | AS11: =IF(M11=0,IF(G11<3,"新客观察期","未激活"),IF(AR11>=90,"SKA",IF(AR11>=75,"KA",IF(AR11>=40,"腰部","基础长尾")))) -> SKA | AT11: =IF(AA11="连续下降","连续下降-预警","") | AU11: =IF(AS11="SKA","守·共创：卡片短信/AI外呼新场景POC",IF(AS11="KA","扩·深化：AI外呼场景深化+Push/企微补全",IF(AS11="腰部","拉·主攻：主推AI外呼+大促作战包",IF(AS11="新客观察期","培育：入门包+1v1场景教育",IF(AS11="基础长尾","激活：企微+Push低成本先跑","唤醒：短信模板+首充补贴"))))) -> 守·共创：卡片短信/AI外呼新场景POC
A12: QA00011 | B12: 安茉香氛 | C12: 美妆个护 | D12: 华东 | E12: 直客 | F12: 2024-07-08 | G12: 23 | H12: 增购客户 | I12: 订阅+消耗 | J12: 1629000 | K12: 576900 | L12: 483200 | M12: =SUM(J12:L12) -> 2689100 | N12: =M12/$M$2002 -> 0.014097983 | O12: =SUM($M$2:M12) -> 50126800 | P12: =O12/$M$2002 -> 0.26279676 | Q12: 332.1 | R12: 21 | S12: 5 | T12: 3 | U12: 107.2 | V12: 24 | W12: 16 | X12: 785 | Y12: 8 | Z12: 2 | AA12: 持平 | AB12: 否 | AC12: =IFERROR(LOOKUP(M12,打分卡!$F$7:$J$7,打分卡!$K$7:$O$7),1) -> 5 | AD12: =IFERROR(LOOKUP(S12,打分卡!$F$8:$J$8,打分卡!$K$8:$O$8),1) -> 5 | AE12: =IFERROR(LOOKUP(T12,打分卡!$F$9:$I$9,打分卡!$K$9:$N$9),1) -> 5 | AF12: =IFERROR(LOOKUP(Q12,打分卡!$F$10:$J$10,打分卡!$K$10:$O$10),1) -> 5 | AG12: =IFERROR(LOOKUP(R12,打分卡!$F$11:$J$11,打分卡!$K$11:$O$11),1) -> 5 | AH12: =IFERROR(LOOKUP(U12,打分卡!$F$12:$J$12,打分卡!$K$12:$O$12),1) -> 5 | AI12: =IFERROR(LOOKUP(X12,打分卡!$F$13:$J$13,打分卡!$K$13:$O$13),1) -> 5 | AJ12: =IFERROR(LOOKUP(Y12,打分卡!$F$14:$J$14,打分卡!$K$14:$O$14),1) -> 5 | AK12: =IFERROR(LOOKUP(W12,打分卡!$F$15:$J$15,打分卡!$K$15:$O$15),1) -> 5 | AL12: =IF(AA12="连续下降",1,IF(AA12="下降",2,IF(AA12="上升",5,3))) -> 3 | AM12: =IFERROR(LOOKUP(Z12,打分卡!$F$17:$H$17,打分卡!$K$17:$M$17),1) -> 5 | AN12: =(打分卡!$D$7*AC12+打分卡!$D$8*AD12+打分卡!$D$9*AE12)/5 -> 40 | AO12: =(打分卡!$D$10*AF12+打分卡!$D$11*AG12)/5 -> 20 | AP12: =(打分卡!$D$12*AH12+打分卡!$D$13*AI12+打分卡!$D$14*AJ12+打分卡!$D$15*AK12)/5 -> 30 | AQ12: =(打分卡!$D$16*AL12+打分卡!$D$17*AM12)/5 -> 7.6 | AR12: =IF(G12<3,AP12/30*40+AO12+AP12+AQ12,AN12+AO12+AP12+AQ12) -> 97.6 | AS12: =IF(M12=0,IF(G12<3,"新客观察期","未激活"),IF(AR12>=90,"SKA",IF(AR12>=75,"KA",IF(AR12>=40,"腰部","基础长尾")))) -> SKA | AT12: =IF(AA12="连续下降","连续下降-预警","") | AU12: =IF(AS12="SKA","守·共创：卡片短信/AI外呼新场景POC",IF(AS12="KA","扩·深化：AI外呼场景深化+Push/企微补全",IF(AS12="腰部","拉·主攻：主推AI外呼+大促作战包",IF(AS12="新客观察期","培育：入门包+1v1场景教育",IF(AS12="基础长尾","激活：企微+Push低成本先跑","唤醒：短信模板+首充补贴"))))) -> 守·共创：卡片短信/AI外呼新场景POC
A13: QA00012 | B13: 芮野优选 | C13: 零售连锁 | D13: 西南 | E13: 直客 | F13: 2025-03-28 | G13: 15 | H13: 流失预警 | I13: 订阅+消耗 | J13: 1179900 | K13: 550600 | L13: 868700 | M13: =SUM(J13:L13) -> 2599200 | N13: =M13/$M$2002 -> 0.01362667 | O13: =SUM($M$2:M13) -> 52726000 | P13: =O13/$M$2002 -> 0.27642343 | Q13: 264.5 | R13: 19 | S13: 5 | T13: 3 | U13: 117.4 | V13: 34 | W13: 19 | X13: 1805 | Y13: 1 | Z13: 3 | AA13: 连续下降 | AB13: 否 | AC13: =IFERROR(LOOKUP(M13,打分卡!$F$7:$J$7,打分卡!$K$7:$O$7),1) -> 5 | AD13: =IFERROR(LOOKUP(S13,打分卡!$F$8:$J$8,打分卡!$K$8:$O$8),1) -> 5 | AE13: =IFERROR(LOOKUP(T13,打分卡!$F$9:$I$9,打分卡!$K$9:$N$9),1) -> 5 | AF13: =IFERROR(LOOKUP(Q13,打分卡!$F$10:$J$10,打分卡!$K$10:$O$10),1) -> 5 | AG13: =IFERROR(LOOKUP(R13,打分卡!$F$11:$J$11,打分卡!$K$11:$O$11),1) -> 5 | AH13: =IFERROR(LOOKUP(U13,打分卡!$F$12:$J$12,打分卡!$K$12:$O$12),1) -> 5 | AI13: =IFERROR(LOOKUP(X13,打分卡!$F$13:$J$13,打分卡!$K$13:$O$13),1) -> 5 | AJ13: =IFERROR(LOOKUP(Y13,打分卡!$F$14:$J$14,打分卡!$K$14:$O$14),1) -> 2 | AK13: =IFERROR(LOOKUP(W13,打分卡!$F$15:$J$15,打分卡!$K$15:$O$15),1) -> 5 | AL13: =IF(AA13="连续下降",1,IF(AA13="下降",2,IF(AA13="上升",5,3))) -> 1 | AM13: =IFERROR(LOOKUP(Z13,打分卡!$F$17:$H$17,打分卡!$K$17:$M$17),1) -> 5 | AN13: =(打分卡!$D$7*AC13+打分卡!$D$8*AD13+打分卡!$D$9*AE13)/5 -> 40 | AO13: =(打分卡!$D$10*AF13+打分卡!$D$11*AG13)/5 -> 20 | AP13: =(打分卡!$D$12*AH13+打分卡!$D$13*AI13+打分卡!$D$14*AJ13+打分卡!$D$15*AK13)/5 -> 26.4 | AQ13: =(打分卡!$D$16*AL13+打分卡!$D$17*AM13)/5 -> 5.2 | AR13: =IF(G13<3,AP13/30*40+AO13+AP13+AQ13,AN13+AO13+AP13+AQ13) -> 91.6 | AS13: =IF(M13=0,IF(G13<3,"新客观察期","未激活"),IF(AR13>=90,"SKA",IF(AR13>=75,"KA",IF(AR13>=40,"腰部","基础长尾")))) -> SKA | AT13: =IF(AA13="连续下降","连续下降-预警","") -> 连续下降-预警 | AU13: =IF(AS13="SKA","守·共创：卡片短信/AI外呼新场景POC",IF(AS13="KA","扩·深化：AI外呼场景深化+Push/企微补全",IF(AS13="腰部","拉·主攻：主推AI外呼+大促作战包",IF(AS13="新客观察期","培育：入门包+1v1场景教育",IF(AS13="基础长尾","激活：企微+Push低成本先跑","唤醒：短信模板+首充补贴"))))) -> 守·共创：卡片短信/AI外呼新场景POC
... A2001: QA02000 | B2001: 星溪乳业 | C2001: 快消食品 | D2001: 华南 | E2001: 渠道代理 | F2001: 2024-06-08 | G2001: 24 | H2001: 已流失 | I2001: 纯消耗 | J2001: 0 | K2001: 0 | L2001: 0 | M2001: =SUM(J2001:L2001) -> 0 | N2001: =M2001/$M$2002 -> 0 | O2001: =SUM($M$2:M2001) -> 190743600 | P2001: =O2001/$M$2002 -> 1 | Q2001: 0 | R2001: 0 | S2001: 0 | T2001: 0 | U2001: 1.5 | V2001: 4 | W2001: 2 | X2001: 59 | Y2001: 1 | Z2001: 0 | AA2001: 连续下降 | AB2001: 否 | AC2001: =IFERROR(LOOKUP(M2001,打分卡!$F$7:$J$7,打分卡!$K$7:$O$7),1) -> 1 | AD2001: =IFERROR(LOOKUP(S2001,打分卡!$F$8:$J$8,打分卡!$K$8:$O$8),1) -> 1 | AE2001: =IFERROR(LOOKUP(T2001,打分卡!$F$9:$I$9,打分卡!$K$9:$N$9),1) -> 1 | AF2001: =IFERROR(LOOKUP(Q2001,打分卡!$F$10:$J$10,打分卡!$K$10:$O$10),1) -> 1 | AG2001: =IFERROR(LOOKUP(R2001,打分卡!$F$11:$J$11,打分卡!$K$11:$O$11),1) -> 1 | AH2001: =IFERROR(LOOKUP(U2001,打分卡!$F$12:$J$12,打分卡!$K$12:$O$12),1) -> 1 | AI2001: =IFERROR(LOOKUP(X2001,打分卡!$F$13:$J$13,打分卡!$K$13:$O$13),1) -> 3 | AJ2001: =IFERROR(LOOKUP(Y2001,打分卡!$F$14:$J$14,打分卡!$K$14:$O$14),1) -> 2 | AK2001: =IFERROR(LOOKUP(W2001,打分卡!$F$15:$J$15,打分卡!$K$15:$O$15),1) -> 2 | AL2001: =IF(AA2001="连续下降",1,IF(AA2001="下降",2,IF(AA2001="上升",5,3))) -> 1 | AM2001: =IFERROR(LOOKUP(Z2001,打分卡!$F$17:$H$17,打分卡!$K$17:$M$17),1) -> 1 | AN2001: =(打分卡!$D$7*AC2001+打分卡!$D$8*AD2001+打分卡!$D$9*AE2001)/5 -> 8 | AO2001: =(打分卡!$D$10*AF2001+打分卡!$D$11*AG2001)/5 -> 4 | AP2001: =(打分卡!$D$12*AH2001+打分卡!$D$13*AI2001+打分卡!$D$14*AJ2001+打分卡!$D$15*AK2001)/5 -> 11.2 | AQ2001: =(打分卡!$D$16*AL2001+打分卡!$D$17*AM2001)/5 -> 2 | AR2001: =IF(G2001<3,AP2001/30*40+AO2001+AP2001+AQ2001,AN2001+AO2001+AP2001+AQ2001) -> 25.2 | AS2001: =IF(M2001=0,IF(G2001<3,"新客观察期","未激活"),IF(AR2001>=90,"SKA",IF(AR2001>=75,"KA",IF(AR2001>=40,"腰部","基础长尾")))) -> 未激活 | AT2001: =IF(AA2001="连续下降","连续下降-预警","") -> 连续下降-预警 | AU2001: =IF(AS2001="SKA","守·共创：卡片短信/AI外呼新场景POC",IF(AS2001="KA","扩·深化：AI外呼场景深化+Push/企微补全",IF(AS2001="腰部","拉·主攻：主推AI外呼+大促作战包",IF(AS2001="新客观察期","培育：入门包+1v1场景教育",IF(AS2001="基础长尾","激活：企微+Push低成本先跑","唤醒：短信模板+首充补贴"))))) -> 唤醒：短信模板+首充补贴
M2002: =SUM(M2:M2001) -> 190743600

Sheet 分层结果与业务动作
B2: 分层结果汇总 与 通道业务动作
B3: 统计口径：基于「商家明细」AP列分层结果，全部为活公式，数据更新后自动重算。
B5: 层级 | C5: 家数 | D5: 家数占比 | E5: 消耗合计(元) | F5: 消耗占比 | G5: 平均综合分 | H5: 平均场景数 | I5: 策略定性
B6: SKA | C6: =COUNTIF(商家明细!$AS$2:$AS$2001,B6) -> 26 | D6: =C6/COUNTA(商家明细!$A$2:$A$2001) -> 0.013 | E6: =SUMIF(商家明细!$AS$2:$AS$2001,B6,商家明细!$M$2:$M$2001) -> 73911300 | F6: =E6/SUM(商家明细!$M$2:$M$2001) -> 0.38749033 | G6: =IFERROR(AVERAGEIF(商家明细!$AS$2:$AS$2001,B6,商家明细!$AR$2:$AR$2001),"-") -> 94.376923 | H6: =IFERROR(AVERAGEIF(商家明细!$AS$2:$AS$2001,B6,商家明细!$S$2:$S$2001),"-") -> 4.7307692 | I6: 守·共创
B7: KA | C7: =COUNTIF(商家明细!$AS$2:$AS$2001,B7) -> 121 | D7: =C7/COUNTA(商家明细!$A$2:$A$2001) -> 0.0605 | E7: =SUMIF(商家明细!$AS$2:$AS$2001,B7,商家明细!$M$2:$M$2001) -> 62513700 | F7: =E7/SUM(商家明细!$M$2:$M$2001) -> 0.32773682 | G7: =IFERROR(AVERAGEIF(商家明细!$AS$2:$AS$2001,B7,商家明细!$AR$2:$AR$2001),"-") -> 81.114601 | H7: =IFERROR(AVERAGEIF(商家明细!$AS$2:$AS$2001,B7,商家明细!$S$2:$S$2001),"-") -> 2.8099174 | I7: 扩·深化
B8: 腰部 | C8: =COUNTIF(商家明细!$AS$2:$AS$2001,B8) -> 695 | D8: =C8/COUNTA(商家明细!$A$2:$A$2001) -> 0.3475 | E8: =SUMIF(商家明细!$AS$2:$AS$2001,B8,商家明细!$M$2:$M$2001) -> 48496800 | F8: =E8/SUM(商家明细!$M$2:$M$2001) -> 0.25425126 | G8: =IFERROR(AVERAGEIF(商家明细!$AS$2:$AS$2001,B8,商家明细!$AR$2:$AR$2001),"-") -> 48.468873 | H8: =IFERROR(AVERAGEIF(商家明细!$AS$2:$AS$2001,B8,商家明细!$S$2:$S$2001),"-") -> 1.8906475 | I8: 拉·主攻
B9: 基础长尾 | C9: =COUNTIF(商家明细!$AS$2:$AS$2001,B9) -> 528 | D9: =C9/COUNTA(商家明细!$A$2:$A$2001) -> 0.264 | E9: =SUMIF(商家明细!$AS$2:$AS$2001,B9,商家明细!$M$2:$M$2001) -> 5821800 | F9: =E9/SUM(商家明细!$M$2:$M$2001) -> 0.030521601 | G9: =IFERROR(AVERAGEIF(商家明细!$AS$2:$AS$2001,B9,商家明细!$AR$2:$AR$2001),"-") -> 33.952399 | H9: =IFERROR(AVERAGEIF(商家明细!$AS$2:$AS$2001,B9,商家明细!$S$2:$S$2001),"-") -> 0.99810606 | I9: 低成本激活
B10: 新客观察期 | C10: =COUNTIF(商家明细!$AS$2:$AS$2001,B10) -> 4 | D10: =C10/COUNTA(商家明细!$A$2:$A$2001) -> 0.002 | E10: =SUMIF(商家明细!$AS$2:$AS$2001,B10,商家明细!$M$2:$M$2001) -> 0 | F10: =E10/SUM(商家明细!$M$2:$M$2001) -> 0 | G10: =IFERROR(AVERAGEIF(商家明细!$AS$2:$AS$2001,B10,商家明细!$AR$2:$AR$2001),"-") -> 77.533333 | H10: =IFERROR(AVERAGEIF(商家明细!$AS$2:$AS$2001,B10,商家明细!$S$2:$S$2001),"-") -> 0 | I10: 培育转化
B11: 未激活 | C11: =COUNTIF(商家明细!$AS$2:$AS$2001,B11) -> 626 | D11: =C11/COUNTA(商家明细!$A$2:$A$2001) -> 0.313 | E11: =SUMIF(商家明细!$AS$2:$AS$2001,B11,商家明细!$M$2:$M$2001) -> 0 | F11: =E11/SUM(商家明细!$M$2:$M$2001) -> 0 | G11: =IFERROR(AVERAGEIF(商家明细!$AS$2:$AS$2001,B11,商家明细!$AR$2:$AR$2001),"-") -> 25.331629 | H11: =IFERROR(AVERAGEIF(商家明细!$AS$2:$AS$2001,B11,商家明细!$S$2:$S$2001),"-") -> 0 | I11: 唤醒/回签
B12: 合计 | C12: =SUM(C6:C11) -> 2000 | E12: =SUM(E6:E11) -> 190743600
B14: 结构验证（金字塔健康度）
B15: SKA家数占比（应<1.5%） | E15: =C6/COUNTA(商家明细!$A$2:$A$2001) -> 0.013
B16: SKA+KA消耗占比（应>60%） | E16: =F6+F7 -> 0.71522714
B17: 预警商家数（连续下降） | E17: =COUNTIF(商家明细!$AT$2:$AT$2001,"连续下降-预警") -> 634
B20: 分层 × 通道拉升动作（业务联动）
B21: 数据洞察：各层通道结构几乎一致（短信≈55%/外呼≈28%/Push企微≈16%），但场景数差异巨大（基础1.5个→SKA 5.0个）——层间差距不在「用哪个通道」，而在「用了几个场景」，通道渗透就是拉升空间。
B22: 层级 | C22: 策略定性 | D22: 通道动作
B23: SKA | C23: 守·共创 | D23: 全场景已铺开，上卡片短信、AI外呼新场景POC（会员生日唤醒等），消耗异常日监控防流失
B24: KA | C24: 扩·深化 | D24: 主打AI外呼深化：大促催付、复购召回两个高客单场景跑透；Push+企微补即时触达，目标场景数→5+
B25: 腰部 | C25: 拉·主攻 | D25: 消耗拉升主战场：短信基本盘已有，优先推AI外呼（客单价高、拉升快）；配「大促作战包」：短信预热+外呼收口+企微返场
B26: 基础长尾 | C26: 低成本激活 | D26: 先用企微+Push（成本最低）跑通触达闭环，验证转化后再上短信；配模板库与自助教程，不配专属小二
B27: 新客观察期 | C27: 培育转化 | D27: 入门包（短信模板+首充补贴）+1v1场景教育，目标3个月内完成首次有效消耗
B28: 未激活 | C28: 唤醒/回签 | D28: 潜客试用给入门包；已流失做断约归因→回签政策，不投运营人力
B30: 迭代机制：月度监测趋势（红灯预警）→ 季度重算综合分 → 连续2个周期跨档才升降级 → 看板盯各层占比、层间迁徙率、各层场景数渗透率。
